curator
setup.cfg
setup.py
SDH_Curator.egg-info/PKG-INFO
SDH_Curator.egg-info/SOURCES.txt
SDH_Curator.egg-info/dependency_links.txt
SDH_Curator.egg-info/namespace_packages.txt
SDH_Curator.egg-info/requires.txt
SDH_Curator.egg-info/top_level.txt
sdh/__init__.py
sdh/curator/__init__.py
sdh/curator/api.py
sdh/curator/metadata.json
sdh/curator/actions/__init__.py
sdh/curator/actions/core/__init__.py
sdh/curator/actions/core/base.py
sdh/curator/actions/core/delivery.py
sdh/curator/actions/core/fragment.py
sdh/curator/actions/core/utils.py
sdh/curator/actions/ext/__init__.py
sdh/curator/actions/ext/enrichment.py
sdh/curator/actions/ext/query.py
sdh/curator/actions/ext/stream.py
sdh/curator/daemons/__init__.py
sdh/curator/daemons/delivery.py
sdh/curator/daemons/fragment.py
sdh/curator/messaging/__init__.py
sdh/curator/messaging/reply.py
sdh/curator/server/__init__.py
sdh/curator/server/config.py
sdh/curator/store/__init__.py
sdh/curator/store/triples.py
sdh/curator/test/__init__.py
sdh/curator/test/enrichment.py
sdh/curator/test/mappings.py
sdh/curator/test/query.py
sdh/curator/test/stream.py