Metadata-Version: 1.1
Name: SDH-Curator
Version: 0.2.32
Summary: The service responsible for supporting resource enrichment on a Linked Data platform
Home-page: https://github.com/smartdeveloperhub/sdh-curator.git
Author: Fernando Serena
Author-email: fernando.serena@centeropenmiddleware.com
License: Apache 2
Download-URL: https://github.com/smartdeveloperhub/sdh-curator/tarball/0.1.15
Keywords: linked-data,ontology,curation
Platform: UNKNOWN
